{
  "app_backend": {
    "webhooks": null
  },
  "connect_permissions": null,
  "distribution_type": "public",
  "icon": "./icon.jpeg",
  "id": "com.example.invoicetemplate",
  "name": "Zendesk Connector",
  "permissions": [
    {
      "permission": "customer_read",
      "purpose": "View customer details to match with Zendesk contacts"
    },
    {
      "permission": "secret_write",
      "purpose": "Store Zendesk API credentials securely"
    }
  ],
  "post_install_action": {
    "type": "settings"
  },
  "ui_extension": {
    "content_security_policy": {
      "connect-src": [
        "https://zsjcivwjghcroaoofnfr.supabase.co/rest/v1/",
        "https://zsjcivwjghcroaoofnfr.supabase.co/auth/v1/",
        "https://zsjcivwjghcroaoofnfr.functions.supabase.co/stripe-app-auth"
      ]
    },
    "views": [
      {
        "component": "CustomerDetailView",
        "viewport": "stripe.dashboard.customer.detail"
      },
      {
        "component": "SettingsView",
        "viewport": "settings"
      }
    ]
  },
  "version": "0.0.12"
}
